kylinautosolve/__init__.py
kylinautosolve/client.py
kylinautosolve/service.py
kylinautosolve/examples/__init__.py
kylinautosolve/examples/cancel.py
kylinautosolve/examples/demo.py
kylinautosolve/examples/poll.py
kylinautosolve/examples/sms.py
kylinautosolve/pb/__init__.py
kylinautosolve/pb/kylinautosolve_pb2.py
kylinautosolve/rpc/__init__.py
kylinautosolve/rpc/transport.py
kylinautosolve-1.0.6.dist-info/LICENSE.txt
kylinautosolve-1.0.6.dist-info/METADATA
kylinautosolve-1.0.6.dist-info/WHEEL
kylinautosolve-1.0.6.dist-info/top_level.txt
kylinautosolve-1.0.6.dist-info/RECORD
