Metadata-Version: 2.1
Name: kylinautosolve
Version: 1.0.6
Summary: The official client package of Kylin Autosolve for Python
Home-page: https://github.com/kylin-public/kylin-autosolve-client-python
Author: Kylin Team
Author-email: kylinbot@gmail.com
License: MIT
Platform: UNKNOWN
Classifier: License :: OSI Approved :: MIT License
Classifier: Programming Language :: Python :: 3
Classifier: Programming Language :: Python :: 3.7
License-File: LICENSE.txt
Requires-Dist: websockets
Requires-Dist: pyee
